JynPopMod/__init__.py
JynPopMod/module.py
JynPopMod-2.8.dist-info/LICENSE
JynPopMod-2.8.dist-info/METADATA
JynPopMod-2.8.dist-info/WHEEL
JynPopMod-2.8.dist-info/top_level.txt
JynPopMod-2.8.dist-info/RECORD
