Metadata-Version: 2.1
Name: JynPopMod
Version: 2.8
Summary: JynPopMod Python Module
Home-page: https://github.com/Jynoqtra/JynPopMod
Author: Jynoqtra
Author-email: Jynoqtra@gmail.com
Classifier: Programming Language :: Python :: 3
Classifier: License :: OSI Approved :: MIT License
Classifier: Intended Audience :: Developers
License-File: LICENSE
Requires-Dist: opencv-python
Requires-Dist: requests
Requires-Dist: pyautogui
Provides-Extra: email_support
Requires-Dist: smtplib; extra == "email-support"
